ohunerin/__init__.py
ohunerin/__main__.py
ohunerin/args.py
ohunerin/audio.py
ohunerin/detector.py
ohunerin/logger.py
ohunerin/models.py
ohunerin/package.py
ohunerin/server.py
ohunerin/wakeword.py
oremi_ohunerin-3.0.0.dist-info/LICENSE
oremi_ohunerin-3.0.0.dist-info/LICENSE_HEADER.txt
oremi_ohunerin-3.0.0.dist-info/METADATA
oremi_ohunerin-3.0.0.dist-info/WHEEL
oremi_ohunerin-3.0.0.dist-info/entry_points.txt
oremi_ohunerin-3.0.0.dist-info/RECORD
