Metadata-Version: 2.3
Name: oremi-ohunerin
Version: 3.0.0
Summary: Real-time ambient sound and wake word detection
Home-page: https://gitlab.com/demsking/oremi-ohunerin
License: Apache-2.0
Keywords: sound,detection,wakeword
Author: Sébastien Demanou
Author-email: demsking@gmail.com
Requires-Python: >=3.11,<3.12
Classifier: Environment :: Console
Classifier: Intended Audience :: Developers
Classifier: License :: OSI Approved :: Apache Software License
Classifier: Natural Language :: English
Classifier: Natural Language :: French
Classifier: Programming Language :: Python :: 3
Classifier: Programming Language :: Python :: 3.11
Classifier: Topic :: Software Development :: Libraries :: Python Modules
Requires-Dist: numpy (>=2.2.2,<3.0.0)
Requires-Dist: oremi-core (>=2.5.3,<3.0.0)
Requires-Dist: pocketsphinx (>=5.0.4,<6.0.0)
Requires-Dist: pydantic (>=2.11.1,<3.0.0)
Requires-Dist: tflite-runtime (>=2.13.0,<3.0.0)
Requires-Dist: tflite-support (>=0.4.4,<0.5.0)
Project-URL: Documentation, https://gitlab.com/demsking/oremi-ohunerin/-/blob/main/README.md
Project-URL: Repository, https://gitlab.com/demsking/oremi-ohunerin
Project-URL: Say Thanks!, https://www.buymeacoffee.com/demsking
Project-URL: Source, https://gitlab.com/demsking/oremi-ohunerin
Project-URL: Tracker, https://gitlab.com/demsking/oremi-ohunerin/-/issues
